replyfast/__init__.py
replyfast/_replyfast.abi3.so
replyfast/scheduler.py
replyfast-0.3.0.dist-info/METADATA
replyfast-0.3.0.dist-info/WHEEL
replyfast-0.3.0.dist-info/licenses/LICENSE
replyfast-0.3.0.dist-info/RECORD
