Metadata-Version: 2.4
Name: replyfast
Version: 0.3.0
Classifier: Development Status :: 3 - Alpha
Classifier: Intended Audience :: Developers
Classifier: Programming Language :: Rust
Classifier: Programming Language :: Python :: 3
Classifier: Programming Language :: Python :: 3.10
Classifier: Programming Language :: Python :: 3.11
Classifier: Programming Language :: Python :: 3.12
Classifier: Programming Language :: Python :: 3.13
Classifier: Programming Language :: Python :: 3.14
Classifier: Programming Language :: Python :: Implementation :: CPython
Classifier: Topic :: Communications :: Chat
Classifier: Topic :: Security :: Cryptography
Requires-Dist: qrcode>=7.0.0 ; extra == 'all'
Requires-Dist: croniter>=2.0.0 ; extra == 'all'
Requires-Dist: maturin>=1.0.0 ; extra == 'dev'
Requires-Dist: ruff ; extra == 'dev'
Requires-Dist: croniter>=2.0.0 ; extra == 'dev'
Requires-Dist: qrcode>=7.0.0 ; extra == 'qrcode'
Requires-Dist: croniter>=2.0.0 ; extra == 'scheduler'
Provides-Extra: all
Provides-Extra: dev
Provides-Extra: qrcode
Provides-Extra: scheduler
License-File: LICENSE
Summary: Signal messaging library for Python using Presage (Rust)
Keywords: signal,messaging,presage,encryption,privacy
Author-email: Kushal Das <mail@kushaldas.in>
Requires-Python: >=3.10
Project-URL: Source, https://github.com/kushaldas/replyfast
